lazy_stats_vx/__init__.py
lazy_stats_vx/lazy_stats.py
lazy_stats_vx-0.1.2.dist-info/METADATA
lazy_stats_vx-0.1.2.dist-info/WHEEL
lazy_stats_vx-0.1.2.dist-info/top_level.txt
lazy_stats_vx-0.1.2.dist-info/RECORD
